<?xml version="1.0" encoding="utf-8"?>
<values><item><id>MZ-P</id><![CDATA[Cabo Delgado]]><value/></item><item><id>MZ-G</id><![CDATA[Gaza]]><value/></item><item><id>MZ-I</id><![CDATA[Inhambane]]><value/></item><item><id>MZ-B</id><![CDATA[Manica]]><value/></item><item><id>MZ-L</id><![CDATA[Maputo]]><value/></item><item><id>MZ-MPM</id><![CDATA[Maputo]]><value/></item><item><id>MZ-N</id><![CDATA[Nampula]]><value/></item><item><id>MZ-A</id><![CDATA[Niassa Province]]><value/></item><item><id>MZ-S</id><![CDATA[Sofala]]><value/></item><item><id>MZ-T</id><![CDATA[Tete]]><value/></item><item><id>MZ-Q</id><![CDATA[Zambezia Province]]><value/></item></values>