<?xml version="1.0" encoding="utf-8"?>
<values><item><id>PS-BTH</id><![CDATA[Bethlehem Bayt Laḩm]]><value/></item><item><id>PS-DEB</id><![CDATA[Deir El Balah Dayr al Balaḩ]]><value/></item><item><id>PS-GZA</id><![CDATA[Gaza Ghazzah]]><value/></item><item><id>PS-HBN</id><![CDATA[Hebron Al Khalīl]]><value/></item><item><id>PS-JEN</id><![CDATA[Jenin Janīn]]><value/></item><item><id>PS-JRH</id><![CDATA[Jericho – Al Aghwar Arīḩā wa al Aghwār]]><value/></item><item><id>PS-JEM</id><![CDATA[Jerusalem Al Quds]]><value/></item><item><id>PS-KYS</id><![CDATA[Khan Yunis Khān Yūnis]]><value/></item><item><id>PS-NBS</id><![CDATA[Nablus Nāblus]]><value/></item><item><id>PS-NGZ</id><![CDATA[North Gaza Shamāl Ghazzah]]><value/></item><item><id>PS-QQA</id><![CDATA[Qalqilya Qalqīlyah]]><value/></item><item><id>PS-RFH</id><![CDATA[Rafah Rafaḩ]]><value/></item><item><id>PS-RBH</id><![CDATA[Ramallah Rām Allāh wa al Bīrah]]><value/></item><item><id>PS-SLT</id><![CDATA[Salfit Salfīt]]><value/></item><item><id>PS-TBS</id><![CDATA[Tubas Ţūbās]]><value/></item><item><id>PS-TKM</id><![CDATA[Tulkarm Ţūlkarm]]><value/></item></values>