<?xml version="1.0" encoding="utf-8"?>
<values><item><id>CH-AG</id><![CDATA[Arg처via]]><value/></item><item><id>CH-AR</id><![CDATA[Appenzell Exterior]]><value/></item><item><id>CH-AI</id><![CDATA[Appenzell Interior]]><value/></item><item><id>CH-BL</id><![CDATA[Basileia-Campo]]><value/></item><item><id>CH-BS</id><![CDATA[Basileia-Cidade]]><value/></item><item><id>CH-BE</id><![CDATA[Berna]]><value/></item><item><id>CH-FR</id><![CDATA[Friburgo]]><value/></item><item><id>CH-GL</id><![CDATA[Glarona]]><value/></item><item><id>CH-GR</id><![CDATA[Gris천es]]><value/></item><item><id>CH-JU</id><![CDATA[Jura]]><value/></item><item><id>CH-NE</id><![CDATA[Neuch창tel]]><value/></item><item><id>CH-NW</id><![CDATA[Nidwald]]><value/></item><item><id>CH-OW</id><![CDATA[Obwald]]><value/></item><item><id>CH-SH</id><![CDATA[Schaffhausen]]><value/></item><item><id>CH-SZ</id><![CDATA[Schwyz]]><value/></item><item><id>CH-SO</id><![CDATA[Soleura]]><value/></item><item><id>CH-TG</id><![CDATA[Turg처via]]><value/></item><item><id>CH-TI</id><![CDATA[Ticino]]><value/></item><item><id>CH-UR</id><![CDATA[Uri]]><value/></item><item><id>CH-VS</id><![CDATA[Valais]]><value/></item><item><id>CH-VD</id><![CDATA[Vaud]]><value/></item><item><id>CH-ZG</id><![CDATA[Zug]]><value/></item><item><id>CH-GE</id><![CDATA[Genebra]]><value/></item><item><id>CH-LU</id><![CDATA[Lucerna]]><value/></item><item><id>CH-ZH</id><![CDATA[Zurique]]><value/></item></values>