{"CA-AB":{"name":"Alberta","level":"province"},"CA-BC":{"name":"Kolumbia Brytyjska","level":"province"},"CA-MB":{"name":"Manitoba","level":"province"},"CA-NB":{"name":"Nowy Brunszwik","level":"province"},"CA-NL":{"name":"Nowa Fundlandia i Labrador","level":"province"},"CA-NT":{"name":"Terytoria Północno-Zachodnie","level":"territory"},"CA-NS":{"name":"Nowa Szkocja","level":"province"},"CA-NU":{"name":"Nunavut","level":"territory"},"CA-ON":{"name":"Ontario","level":"province"},"CA-PE":{"name":"Wyspa Księcia Edwarda","level":"province"},"CA-QC":{"name":"Quebec","level":"province"},"CA-SK":{"name":"Saskatchewan","level":"province"},"CA-YT":{"name":"Jukon","level":"territory"}}
