{"CV-BV":{"name":"Boa Vista","level":"municipality"},"CV-BR":{"name":"Brava","level":"municipality"},"CV-CS":{"name":"Calheta de São Miguel","level":""},"CV-B":{"name":"Barlavento Islands","level":"geographical region"},"CV-S":{"name":"Sotavento Islands","level":"geographical region"},"CV-MA":{"name":"Maio","level":"municipality"},"CV-MO":{"name":"Mosteiros","level":"municipality"},"CV-PA":{"name":"Paul","level":"municipality"},"CV-PN":{"name":"Porto-Novo","level":"municipality"},"CV-PR":{"name":"Praia","level":"municipality"},"CV-RB":{"name":"Ribeira Brava","level":"municipality"},"CV-RG":{"name":"Ribeira Grande","level":"municipality"},"CV-RS":{"name":"Ribeira Grande de Santiago","level":"municipality"},"CV-SL":{"name":"Sal","level":"municipality"},"CV-CA":{"name":"Santa Catarina","level":"municipality"},"CV-CF":{"name":"Santa Catarina do Fogo","level":"municipality"},"CV-CR":{"name":"Santa Cruz","level":"municipality"},"CV-SD":{"name":"São Domingos","level":"municipality"},"CV-SF":{"name":"Saint Philip","level":"municipality"},"CV-SO":{"name":"São Lourenço dos Órgãos","level":"municipality"},"CV-SM":{"name":"São Miguel","level":"municipality"},"CV-SN":{"name":"São Nicolau","level":""},"CV-SS":{"name":"São Salvador do Mundo","level":"municipality"},"CV-SV":{"name":"São Vicente","level":"municipality"},"CV-TA":{"name":"Tarrafal","level":"municipality"},"CV-TS":{"name":"Tarrafal de São Nicolau","level":"municipality"}}
